watchmen_storage_adls/__init__.py
watchmen_storage_adls/adls_storage_service.py
watchmen_storage_adls/data_source_adls.py
watchmen_storage_adls/object_defs_adls.py
watchmen_storage_adls/storage_adls.py
watchmen_storage_adls/storage_adls_configuration.py
watchmen_storage_adls-18.0.1.dist-info/METADATA
watchmen_storage_adls-18.0.1.dist-info/WHEEL
watchmen_storage_adls-18.0.1.dist-info/licenses/LICENSE
watchmen_storage_adls-18.0.1.dist-info/RECORD
