Metadata-Version: 2.4
Name: watchmen-storage-adls
Version: 18.0.1
Summary: 
License: MIT
License-File: LICENSE
Author: botlikes
Author-email: 75356972+botlikes456@users.noreply.github.com
Requires-Python: >=3.12,<3.13
Classifier: License :: OSI Approved :: MIT License
Classifier: Programming Language :: Python :: 3
Classifier: Programming Language :: Python :: 3.12
Requires-Dist: azure-identity (>=1.16.0,<2.0.0)
Requires-Dist: azure-storage-file-datalake (>=12.14.0,<13.0.0)
Requires-Dist: watchmen-storage (==18.0.1)
